dickerbotclient/__init__.py
dickerbotclient/client.py
dickerbotclient-1.0.2.dist-info/licenses/LICENSE
dickerbotclient-1.0.2.dist-info/METADATA
dickerbotclient-1.0.2.dist-info/WHEEL
dickerbotclient-1.0.2.dist-info/top_level.txt
dickerbotclient-1.0.2.dist-info/RECORD
