Metadata-Version: 2.4
Name: dickerbotclient
Version: 1.0.2
Summary: Python client library for communicating with DickerBot robots.
Author-email: Keshav Shankar <keshavshankar08@gmail.com>
License-Expression: MIT
Project-URL: Homepage, https://github.com/keshavshankar08/DickerBot/tree/main/DickerBotClient
Project-URL: Issues, https://github.com/keshavshankar08/DickerBot/issues
Requires-Python: >=3.7
License-File: LICENSE
Requires-Dist: websockets
Requires-Dist: numpy
Dynamic: license-file
